edb_mpris/__init__.py
edb_mpris/event.py
el_decko_backend_mpris-2023.5.6.1.dist-info/LICENSE
el_decko_backend_mpris-2023.5.6.1.dist-info/METADATA
el_decko_backend_mpris-2023.5.6.1.dist-info/WHEEL
el_decko_backend_mpris-2023.5.6.1.dist-info/entry_points.txt
el_decko_backend_mpris-2023.5.6.1.dist-info/top_level.txt
el_decko_backend_mpris-2023.5.6.1.dist-info/RECORD
