Metadata-Version: 2.1
Name: el-decko-backend-mpris
Version: 2023.5.6.1
Summary: El Decko backend to control MPRIS2 compatible media players
Author-email: Imo 'Vortex Acherontic' Hester <vortex@z-ray.de>
License: GPL-3
Project-URL: Homepage, https://github.com/Z-Ray-Entertainment/el_decko_backend_mpris
Project-URL: Bug Tracker, https://github.com/Z-Ray-Entertainment/el_decko_backend_mpris/issues
Platform: Linux
Requires-Python: >=3.8
License-File: LICENSE
Requires-Dist: pympris
Requires-Dist: dbus-python (>=1.0)
